metatrim/__init__.py
metatrim/command_line.py
metatrim/metatrim.py
metatrim/metatrim_module.py
metatrim-1.0.4.dist-info/LICENSE
metatrim-1.0.4.dist-info/METADATA
metatrim-1.0.4.dist-info/WHEEL
metatrim-1.0.4.dist-info/entry_points.txt
metatrim-1.0.4.dist-info/top_level.txt
metatrim-1.0.4.dist-info/RECORD
