Metadata-Version: 2.1
Name: metatrim
Version: 1.0.4
Summary: Trim reads from metabarcoding libraries
Home-page: https://github.com/msnyder424/HTS-eDNA-Bioinformatics/tree/master/metatrim
Author: Matt Snyder
Keywords: metabarcoding,environmental DNA,eDNA,high-throughput sequencing,HTS,next-generation sequencing,NGS
Classifier: Programming Language :: Python :: 3
Classifier: License :: OSI Approved :: MIT License
Classifier: Operating System :: OS Independent
Requires-Python: <4,>=3.6
License-File: LICENSE
